launchkey/__init__.py
launchkey/clients/__init__.py
launchkey/clients/base.py
launchkey/clients/directory.py
launchkey/clients/organization.py
launchkey/clients/service.py
launchkey/entities/__init__.py
launchkey/entities/directory.py
launchkey/entities/shared.py
launchkey/entities/validation.py
launchkey/entities/service/__init__.py
launchkey/entities/service/policy.py
launchkey/exceptions/__init__.py
launchkey/exceptions/validation.py
launchkey/factories/__init__.py
launchkey/factories/base.py
launchkey/factories/directory.py
launchkey/factories/organization.py
launchkey/factories/service.py
launchkey/transports/__init__.py
launchkey/transports/base.py
launchkey/transports/http.py
launchkey/transports/jose_auth.py
launchkey/utils/__init__.py
launchkey/utils/shared.py
launchkey/utils/validation.py
launchkey-4.0.1.dist-info/LICENSE.txt
launchkey-4.0.1.dist-info/METADATA
launchkey-4.0.1.dist-info/WHEEL
launchkey-4.0.1.dist-info/top_level.txt
launchkey-4.0.1.dist-info/RECORD
