Metadata-Version: 2.1
Name: launchkey
Version: 4.0.1
Summary: LaunchKey Python SDK
Home-page: https://github.com/iovation/launchkey-python
Author: iovation
License: MIT
Project-URL: Bug Reports, https://github.com/iovation/launchkey-python/issues
Project-URL: Documentation, https://docs.launchkey.com/service-sdk/python/sdk-v3/
Project-URL: Administration, https://admin.launchkey.com/
Keywords: launchkey security authentication iovation multifactor mfa 2fa biometric
Classifier: Programming Language :: Python
Classifier: License :: OSI Approved :: MIT License
Classifier: Operating System :: OS Independent
Classifier: Topic :: System :: Systems Administration :: Authentication/Directory
Classifier: Programming Language :: Python :: Implementation :: CPython
Classifier: Programming Language :: Python :: Implementation :: PyPy
Classifier: Programming Language :: Python :: 3
Classifier: Programming Language :: Python :: 3.7
Classifier: Programming Language :: Python :: 3.8
Classifier: Programming Language :: Python :: 3.9
Classifier: Programming Language :: Python :: 3.10
Classifier: Natural Language :: English
Classifier: Intended Audience :: Developers
License-File: LICENSE.txt
Requires-Dist: setuptools (>=40.4.3)
Requires-Dist: requests (<3.0.0,>=2.5.1)
Requires-Dist: python-dateutil (<3.0.0,>=2.4.2)
Requires-Dist: formencode (<3.0.0,>=2.0.0)
Requires-Dist: pyjwkest (<2.0.0,>=1.3.2)
Requires-Dist: pycryptodomex (<4.0.0,>=3.4.12)
Requires-Dist: urllib3 (<2.0.0,>=1.26.5)
Requires-Dist: pytz
